pygcards/__init__.py
pygcards/black_jack.py
pygcards/card.py
pygcards/card_game.py
pygcards/deck.py
pygcards/game_state.py
pygcards/hand.py
pygcards/player.py
pygcards_pkg/__init__.py
pygcards_pygdev-0.0.5.data/scripts/pyg-blackjack
tests/__init__.py
tests/context.py
tests/test_basic.py
pygcards_pygdev-0.0.5.dist-info/LICENSE
pygcards_pygdev-0.0.5.dist-info/METADATA
pygcards_pygdev-0.0.5.dist-info/WHEEL
pygcards_pygdev-0.0.5.dist-info/top_level.txt
pygcards_pygdev-0.0.5.dist-info/RECORD
