Metadata-Version: 2.1
Name: pygcards-pygdev
Version: 0.0.5
Summary: A cards framework for python
Home-page: https://github.com/g4k13/pygcards
Author: pygdev
Author-email: g4k13@github.com
License: UNKNOWN
Platform: UNKNOWN
Classifier: Programming Language :: Python :: 3
Classifier: License :: OSI Approved :: MIT License
Classifier: Operating System :: OS Independent
